RoboOps/RoboOps.py
RoboOps/__init__.py
robotframework_roboops-0.2.4.dist-info/LICENSE
robotframework_roboops-0.2.4.dist-info/WHEEL
robotframework_roboops-0.2.4.dist-info/METADATA
robotframework_roboops-0.2.4.dist-info/RECORD
